package/__init__.py
package/sinuiMSAI.py
sinuiMSAI-1.0.dist-info/METADATA
sinuiMSAI-1.0.dist-info/WHEEL
sinuiMSAI-1.0.dist-info/top_level.txt
sinuiMSAI-1.0.dist-info/RECORD
